checkout_intents/__init__.py
checkout_intents/_base_client.py
checkout_intents/_client.py
checkout_intents/_compat.py
checkout_intents/_constants.py
checkout_intents/_exceptions.py
checkout_intents/_files.py
checkout_intents/_models.py
checkout_intents/_qs.py
checkout_intents/_resource.py
checkout_intents/_response.py
checkout_intents/_streaming.py
checkout_intents/_types.py
checkout_intents/_version.py
checkout_intents/pagination.py
checkout_intents/py.typed
checkout_intents/_utils/__init__.py
checkout_intents/_utils/_compat.py
checkout_intents/_utils/_datetime_parse.py
checkout_intents/_utils/_json.py
checkout_intents/_utils/_logs.py
checkout_intents/_utils/_proxy.py
checkout_intents/_utils/_reflection.py
checkout_intents/_utils/_resources_proxy.py
checkout_intents/_utils/_streams.py
checkout_intents/_utils/_sync.py
checkout_intents/_utils/_transform.py
checkout_intents/_utils/_typing.py
checkout_intents/_utils/_utils.py
checkout_intents/lib/.keep
checkout_intents/resources/__init__.py
checkout_intents/resources/brands.py
checkout_intents/resources/checkout_intents.py
checkout_intents/resources/products.py
checkout_intents/resources/betas/__init__.py
checkout_intents/resources/betas/betas.py
checkout_intents/resources/betas/checkout_sessions.py
checkout_intents/types/__init__.py
checkout_intents/types/base_checkout_intent.py
checkout_intents/types/brand_retrieve_response.py
checkout_intents/types/buyer.py
checkout_intents/types/buyer_param.py
checkout_intents/types/checkout_intent.py
checkout_intents/types/checkout_intent_add_payment_params.py
checkout_intents/types/checkout_intent_confirm_params.py
checkout_intents/types/checkout_intent_create_params.py
checkout_intents/types/checkout_intent_list_params.py
checkout_intents/types/checkout_intent_purchase_params.py
checkout_intents/types/checkout_session.py
checkout_intents/types/money.py
checkout_intents/types/offer.py
checkout_intents/types/payment_method.py
checkout_intents/types/payment_method_param.py
checkout_intents-0.13.1.dist-info/METADATA
checkout_intents-0.13.1.dist-info/WHEEL
checkout_intents-0.13.1.dist-info/licenses/LICENSE
checkout_intents-0.13.1.dist-info/RECORD
